benpy.cp310-win_amd64.pyd
gsl.dll
gslcblas.dll
benpy-2.5.1.dist-info/LICENSE
benpy-2.5.1.dist-info/METADATA
benpy-2.5.1.dist-info/WHEEL
benpy-2.5.1.dist-info/top_level.txt
benpy-2.5.1.dist-info/RECORD
