Metadata-Version: 2.1
Name: benpy
Version: 2.5.1
Summary: Bentham Spectral Analysis and Calibration Utilities Library
Home-page: https://github.com/BenthamInstruments/BenAnalysis
Author: Bentham Instruments Ltd
Author-email: support@bentham.com
License-File: LICENSE
